{
    "indexes": {
        "jobs": {
            "0": {
                "batch_id": "zysj",
                "crawl_http_method": "get",
                "crawl_gap": 0.5,
                "crawl_use_js_engine": false,
                "length": 500,
                "priority": 2,
                "crawl_timeout": 10,
                "failure_times": 6,
                "filename_urls": "/home/admin/hcrawler/zysj_pages.txt",
                "url_pattern": "http://www.zysj.com.cn/zhongyaocai/index__{}.html"
            },
            "1": {
                "batch_id": "chem",
                "crawl_http_method": "get",
                "crawl_gap": 1,
                "crawl_use_js_engine": false,
                "length": 340,
                "priority": 2,
                "crawl_timeout": 10,
                "failure_times": 6,
                "filename_urls": "/home/admin/hcrawler/alphas_for_search.txt",
                "url_pattern": "http://china.chemnet.com/hot-product/{}.html"
            }
        },
        "aws_machine_number": 20,
        "note": "monthly",
        "debug": false
    }
}
